codex/__init__.py
codex/bundles.py
codex/device_controls.py
codex/device_manager.py
codex/subscriptions.py
codex/devices/__init__.py
codex/devices/console_device.py
codex/devices/serial_device.py
codex/devices/serial_device_base.py
codex/devices/unknown_device.py
codex/drivers/__init__.py
codex/drivers/dummy_serial.py
codex/drivers/local_serial.py
codex/drivers/remote_serial.py
codex/filters/__init__.py
codex/filters/delimiter_filter.py
codex/filters/judi_filter.py
codex/filters/newline_filter.py
codex/filters/null_filter.py
codex/judi/__init__.py
codex/judi/judi_mixin.py
codex/judi/judi_responder.py
codex_engine_pyqt-0.3.1.dist-info/LICENSE
codex_engine_pyqt-0.3.1.dist-info/METADATA
codex_engine_pyqt-0.3.1.dist-info/WHEEL
codex_engine_pyqt-0.3.1.dist-info/top_level.txt
codex_engine_pyqt-0.3.1.dist-info/RECORD
