Metadata-Version: 2.1
Name: codex-engine-pyqt
Version: 0.3.1
Summary: A universal translator for serial devices.
Author-email: David Kincaid <daelonsuzuka@gmail.com>
License: MIT License
Project-URL: Homepage, https://github.com/Codex-Engine/codex-engine-pyqt
Project-URL: Repository, https://github.com/Codex-Engine/codex-engine-pyqt
Project-URL: Issues, https://github.com/Codex-Engine/codex-engine-pyqt/issues
Classifier: Development Status :: 4 - Beta
Classifier: Intended Audience :: Developers
Classifier: Topic :: Software Development :: Widget Sets
Classifier: Operating System :: OS Independent
Classifier: License :: OSI Approved :: MIT License
Classifier: Programming Language :: Python :: 3
Classifier: Programming Language :: Python :: 3.9
Classifier: Programming Language :: Python :: 3.10
Classifier: Programming Language :: Python :: 3.11
Classifier: Programming Language :: Python :: 3.12
Classifier: Programming Language :: Python :: 3.13
Requires-Python: >=3.9
License-File: LICENSE
Requires-Dist: pyserial
Requires-Dist: qtstrap
